odoo8_addon_web_readonly_bypass-8.0.1.0.1.99.dev4-py2.7-nspkg.pth
odoo8_addon_web_readonly_bypass-8.0.1.0.1.99.dev4.dist-info/METADATA
odoo8_addon_web_readonly_bypass-8.0.1.0.1.99.dev4.dist-info/RECORD
odoo8_addon_web_readonly_bypass-8.0.1.0.1.99.dev4.dist-info/WHEEL
odoo8_addon_web_readonly_bypass-8.0.1.0.1.99.dev4.dist-info/namespace_packages.txt
odoo8_addon_web_readonly_bypass-8.0.1.0.1.99.dev4.dist-info/top_level.txt
odoo_addons/web_readonly_bypass/README.rst
odoo_addons/web_readonly_bypass/__init__.py
odoo_addons/web_readonly_bypass/__openerp__.py
odoo_addons/web_readonly_bypass/i18n/web_readonly_bypass.pot
odoo_addons/web_readonly_bypass/static/description/icon.png
odoo_addons/web_readonly_bypass/static/src/js/readonly_bypass.js
odoo_addons/web_readonly_bypass/static/test/web_readonly_bypass.js
odoo_addons/web_readonly_bypass/views/readonly_bypass.xml
